README.md
setup.py
optiml/__init__.py
optiml.egg-info/PKG-INFO
optiml.egg-info/SOURCES.txt
optiml.egg-info/dependency_links.txt
optiml.egg-info/requires.txt
optiml.egg-info/top_level.txt
optiml/ml/__init__.py
optiml/ml/utils.py
optiml/ml/neural_network/__init__.py
optiml/ml/neural_network/_base.py
optiml/ml/neural_network/activations.py
optiml/ml/neural_network/initializers.py
optiml/ml/neural_network/layers.py
optiml/ml/neural_network/losses.py
optiml/ml/neural_network/regularizers.py
optiml/ml/svm/__init__.py
optiml/ml/svm/_base.py
optiml/ml/svm/kernels.py
optiml/ml/svm/losses.py
optiml/ml/svm/smo.py
optiml/ml/tests/__init__.py
optiml/ml/tests/test_neural_network.py
optiml/ml/tests/test_svc.py
optiml/ml/tests/test_svr.py
optiml/opti/__init__.py
optiml/opti/_base.py
optiml/opti/utils.py
optiml/opti/constrained/__init__.py
optiml/opti/constrained/_base.py
optiml/opti/constrained/active_set.py
optiml/opti/constrained/frank_wolfe.py
optiml/opti/constrained/interior_point.py
optiml/opti/constrained/projected_gradient.py
optiml/opti/constrained/tests/__init__.py
optiml/opti/constrained/tests/test_active_set.py
optiml/opti/constrained/tests/test_frank_wolfe.py
optiml/opti/constrained/tests/test_interior_point.py
optiml/opti/constrained/tests/test_lagrangian_quadratic.py
optiml/opti/constrained/tests/test_projected_gradient.py
optiml/opti/unconstrained/__init__.py
optiml/opti/unconstrained/_base.py
optiml/opti/unconstrained/proximal_bundle.py
optiml/opti/unconstrained/line_search/__init__.py
optiml/opti/unconstrained/line_search/_base.py
optiml/opti/unconstrained/line_search/conjugate_gradient.py
optiml/opti/unconstrained/line_search/gradient_descent.py
optiml/opti/unconstrained/line_search/line_search.py
optiml/opti/unconstrained/line_search/newton.py
optiml/opti/unconstrained/line_search/quasi_newton.py
optiml/opti/unconstrained/stochastic/__init__.py
optiml/opti/unconstrained/stochastic/_base.py
optiml/opti/unconstrained/stochastic/adadelta.py
optiml/opti/unconstrained/stochastic/adagrad.py
optiml/opti/unconstrained/stochastic/adam.py
optiml/opti/unconstrained/stochastic/adamax.py
