Metadata-Version: 2.1
Name: optiml
Version: 1.5
Summary: Optimizers for/and sklearn compatible Machine Learning models
Home-page: https://github.com/dmeoli/optiml
Author: Donato Meoli
Author-email: donato.meoli.95@gmail.com
License: MIT
Platform: UNKNOWN
Requires-Python: >=3.6
